ItarjConsole/__init__.py
ItarjConsole/itarj.py
ItarjConsole-0.3.2.dist-info/LICENSE
ItarjConsole-0.3.2.dist-info/METADATA
ItarjConsole-0.3.2.dist-info/WHEEL
ItarjConsole-0.3.2.dist-info/top_level.txt
ItarjConsole-0.3.2.dist-info/RECORD
