Metadata-Version: 2.1
Name: ItarjConsole
Version: 0.3.2
Summary: A CLI application created with Python that allows users to create posts of fake job alerts and allows user to also search the database for these posts using keywords
Home-page: https://github.com/startng/forward-itarj-damianson
Author: Uchegbu Damianson-Wisdom
Author-email: damiansonuchegbu2017@gmail.com
License: MIT
Platform: UNKNOWN
Classifier: Programming Language :: Python
Classifier: License :: OSI Approved :: MIT License
Classifier: Operating System :: OS Independent
Requires-Dist: click
Requires-Dist: pyfiglet
Requires-Dist: mysql-connector-python
Requires-Dist: colorama
